moist_thermodynamics/__init__.py
moist_thermodynamics/constants.py
moist_thermodynamics/constants_icon.py
moist_thermodynamics/functions.py
moist_thermodynamics/saturation_vapor_pressures.py
moist_thermodynamics/utilities.py
moist_thermodynamics-0.0.5.dist-info/METADATA
moist_thermodynamics-0.0.5.dist-info/WHEEL
moist_thermodynamics-0.0.5.dist-info/licenses/LICENSE
moist_thermodynamics-0.0.5.dist-info/RECORD
