Metadata-Version: 2.4
Name: moist_thermodynamics
Version: 0.0.5
Summary: Constants and functions for the treatment of moist atmospheric thermodynamics.
Author-email: Bjorn Stevens <bjorn.stevens@mpimet.mpg.de>
License-Expression: BSD-3-Clause
License-File: LICENSE
Requires-Python: >=3.10
Requires-Dist: numpy
Requires-Dist: scipy
